MANIFEST.in
README.txt
setup.py
c2/__init__.py
c2.search.fuzzy.egg-info/PKG-INFO
c2.search.fuzzy.egg-info/SOURCES.txt
c2.search.fuzzy.egg-info/dependency_links.txt
c2.search.fuzzy.egg-info/entry_points.txt
c2.search.fuzzy.egg-info/namespace_packages.txt
c2.search.fuzzy.egg-info/not-zip-safe
c2.search.fuzzy.egg-info/requires.txt
c2.search.fuzzy.egg-info/top_level.txt
c2/search/__init__.py
c2/search/fuzzy/__init__.py
c2/search/fuzzy/automata.py
c2/search/fuzzy/configure.zcml
c2/search/fuzzy/events.py
c2/search/fuzzy/sql_connection.py
c2/search/fuzzy/tests.py
c2/search/fuzzy/version.txt
c2/search/fuzzy/words_for_fuzzy_model.py
c2/search/fuzzy/words_for_fuzzy_tool.py
c2/search/fuzzy/browser/__init__.py
c2/search/fuzzy/browser/configure.zcml
c2/search/fuzzy/browser/controlpanel.pt
c2/search/fuzzy/browser/controlpanel.py
c2/search/fuzzy/browser/fuzzy_search.pt
c2/search/fuzzy/browser/fuzzy_search.py
c2/search/fuzzy/browser/resource/fuzzy_search.js
c2/search/fuzzy/locales/c2.search.fuzzy.pot
c2/search/fuzzy/locales/en/LC_MESSAGES/c2.search.fuzzy.mo
c2/search/fuzzy/locales/en/LC_MESSAGES/c2.search.fuzzy.po
c2/search/fuzzy/locales/ja/LC_MESSAGES/c2.search.fuzzy.mo
c2/search/fuzzy/locales/ja/LC_MESSAGES/c2.search.fuzzy.po
c2/search/fuzzy/profiles/default/controlpanel.xml
c2/search/fuzzy/profiles/default/jsregistry.xml
c2/search/fuzzy/profiles/default/skins.xml
c2/search/fuzzy/profiles/default/toolset.xml
c2/search/fuzzy/skins/c2SearchFuzzy/search.pt
docs/HISTORY.txt
docs/INSTALL.txt
docs/LICENSE.GPL
docs/LICENSE.txt