Metadata-Version: 1.1
Name: c2.search.fuzzy
Version: 1.0a6
Summary: This product is adding fuzzy search function for Plone
Home-page: http://www.cmscom.jp
Author: Manabu TERADA
Author-email: terada@cmscom.jp
License: GPL
Keywords: plone fuzzy search
Platform: UNKNOWN
Classifier: Framework :: Plone
Classifier: Programming Language :: Python
